{"frames":{"Idle0000":{"frame":{"x":10,"y":6,"w":13,"h":19},"rotated":false,"trimmed":false,"spriteSourceSize":{"x":0,"y":0,"w":13,"h":19},"sourceSize":{"w":13,"h":19}},"Idle0003":{"frame":{"x":110,"y":6,"w":15,"h":19},"rotated":false,"trimmed":false,"spriteSourceSize":{"x":0,"y":0,"w":15,"h":19},"sourceSize":{"w":15,"h":19}},"Left0001":{"frame":{"x":177,"y":6,"w":17,"h":20},"rotated":false,"trimmed":false,"spriteSourceSize":{"x":0,"y":0,"w":17,"h":20},"sourceSize":{"w":17,"h":20}},"Left0005":{"frame":{"x":318,"y":6,"w":17,"h":20},"rotated":false,"trimmed":false,"spriteSourceSize":{"x":0,"y":0,"w":17,"h":20},"sourceSize":{"w":17,"h":20}},"Idle0001":{"frame":{"x":42,"y":7,"w":15,"h":18},"rotated":false,"trimmed":false,"spriteSourceSize":{"x":0,"y":0,"w":15,"h":18},"sourceSize":{"w":15,"h":18}},"Idle0002":{"frame":{"x":75,"y":7,"w":16,"h":18},"rotated":false,"trimmed":false,"spriteSourceSize":{"x":0,"y":0,"w":16,"h":18},"sourceSize":{"w":16,"h":18}},"Left0000":{"frame":{"x":144,"y":7,"w":15,"h":19},"rotated":false,"trimmed":false,"spriteSourceSize":{"x":0,"y":0,"w":15,"h":19},"sourceSize":{"w":15,"h":19}},"Left0002":{"frame":{"x":212,"y":7,"w":16,"h":19},"rotated":false,"trimmed":false,"spriteSourceSize":{"x":0,"y":0,"w":16,"h":19},"sourceSize":{"w":16,"h":19}},"Left0003":{"frame":{"x":246,"y":7,"w":17,"h":19},"rotated":false,"trimmed":false,"spriteSourceSize":{"x":0,"y":0,"w":17,"h":19},"sourceSize":{"w":17,"h":19}},"Left0004":{"frame":{"x":282,"y":7,"w":17,"h":19},"rotated":false,"trimmed":false,"spriteSourceSize":{"x":0,"y":0,"w":17,"h":19},"sourceSize":{"w":17,"h":19}},"Right0001":{"frame":{"x":113,"y":40,"w":16,"h":20},"rotated":false,"trimmed":false,"spriteSourceSize":{"x":0,"y":0,"w":16,"h":20},"sourceSize":{"w":16,"h":20}},"Right0005":{"frame":{"x":243,"y":40,"w":17,"h":20},"rotated":false,"trimmed":false,"spriteSourceSize":{"x":0,"y":0,"w":17,"h":20},"sourceSize":{"w":17,"h":20}},"Left0006":{"frame":{"x":11,"y":41,"w":14,"h":19},"rotated":false,"trimmed":false,"spriteSourceSize":{"x":0,"y":0,"w":14,"h":19},"sourceSize":{"w":14,"h":19}},"Left0007":{"frame":{"x":45,"y":41,"w":13,"h":19},"rotated":false,"trimmed":false,"spriteSourceSize":{"x":0,"y":0,"w":13,"h":19},"sourceSize":{"w":13,"h":19}},"Right0000":{"frame":{"x":80,"y":41,"w":13,"h":20},"rotated":false,"trimmed":false,"spriteSourceSize":{"x":0,"y":0,"w":13,"h":20},"sourceSize":{"w":13,"h":20}},"Right0002":{"frame":{"x":146,"y":41,"w":16,"h":19},"rotated":false,"trimmed":false,"spriteSourceSize":{"x":0,"y":0,"w":16,"h":19},"sourceSize":{"w":16,"h":19}},"Right0003":{"frame":{"x":178,"y":41,"w":17,"h":19},"rotated":false,"trimmed":false,"spriteSourceSize":{"x":0,"y":0,"w":17,"h":19},"sourceSize":{"w":17,"h":19}},"Right0004":{"frame":{"x":211,"y":41,"w":17,"h":19},"rotated":false,"trimmed":false,"spriteSourceSize":{"x":0,"y":0,"w":17,"h":19},"sourceSize":{"w":17,"h":19}},"Right0006":{"frame":{"x":281,"y":41,"w":15,"h":19},"rotated":false,"trimmed":false,"spriteSourceSize":{"x":0,"y":0,"w":15,"h":19},"sourceSize":{"w":15,"h":19}},"Right0007":{"frame":{"x":314,"y":41,"w":16,"h":20},"rotated":false,"trimmed":false,"spriteSourceSize":{"x":0,"y":0,"w":16,"h":20},"sourceSize":{"w":16,"h":20}},"Up0000":{"frame":{"x":11,"y":74,"w":11,"h":20},"rotated":false,"trimmed":false,"spriteSourceSize":{"x":0,"y":0,"w":11,"h":20},"sourceSize":{"w":11,"h":20}},"Up0001":{"frame":{"x":45,"y":74,"w":12,"h":20},"rotated":false,"trimmed":false,"spriteSourceSize":{"x":0,"y":0,"w":12,"h":20},"sourceSize":{"w":12,"h":20}},"Up0003":{"frame":{"x":113,"y":74,"w":13,"h":20},"rotated":false,"trimmed":false,"spriteSourceSize":{"x":0,"y":0,"w":13,"h":20},"sourceSize":{"w":13,"h":20}},"Up0004":{"frame":{"x":147,"y":74,"w":12,"h":20},"rotated":false,"trimmed":false,"spriteSourceSize":{"x":0,"y":0,"w":12,"h":20},"sourceSize":{"w":12,"h":20}},"Up0005":{"frame":{"x":182,"y":74,"w":10,"h":20},"rotated":false,"trimmed":false,"spriteSourceSize":{"x":0,"y":0,"w":10,"h":20},"sourceSize":{"w":10,"h":20}},"Up0007":{"frame":{"x":248,"y":74,"w":12,"h":21},"rotated":false,"trimmed":false,"spriteSourceSize":{"x":0,"y":0,"w":12,"h":21},"sourceSize":{"w":12,"h":21}},"Up0008":{"frame":{"x":284,"y":74,"w":10,"h":21},"rotated":false,"trimmed":false,"spriteSourceSize":{"x":0,"y":0,"w":10,"h":21},"sourceSize":{"w":10,"h":21}},"Down0000":{"frame":{"x":317,"y":74,"w":10,"h":21},"rotated":false,"trimmed":false,"spriteSourceSize":{"x":0,"y":0,"w":10,"h":21},"sourceSize":{"w":10,"h":21}},"Up0002":{"frame":{"x":80,"y":75,"w":11,"h":19},"rotated":false,"trimmed":false,"spriteSourceSize":{"x":0,"y":0,"w":11,"h":19},"sourceSize":{"w":11,"h":19}},"Up0006":{"frame":{"x":215,"y":75,"w":11,"h":20},"rotated":false,"trimmed":false,"spriteSourceSize":{"x":0,"y":0,"w":11,"h":20},"sourceSize":{"w":11,"h":20}},"Down0001":{"frame":{"x":11,"y":108,"w":10,"h":21},"rotated":false,"trimmed":false,"spriteSourceSize":{"x":0,"y":0,"w":10,"h":21},"sourceSize":{"w":10,"h":21}},"Down0003":{"frame":{"x":79,"y":108,"w":10,"h":21},"rotated":false,"trimmed":false,"spriteSourceSize":{"x":0,"y":0,"w":10,"h":21},"sourceSize":{"w":10,"h":21}},"Down0004":{"frame":{"x":113,"y":108,"w":10,"h":21},"rotated":false,"trimmed":false,"spriteSourceSize":{"x":0,"y":0,"w":10,"h":21},"sourceSize":{"w":10,"h":21}},"Down0005":{"frame":{"x":148,"y":108,"w":9,"h":21},"rotated":false,"trimmed":false,"spriteSourceSize":{"x":0,"y":0,"w":9,"h":21},"sourceSize":{"w":9,"h":21}},"Down0007":{"frame":{"x":216,"y":108,"w":9,"h":21},"rotated":false,"trimmed":false,"spriteSourceSize":{"x":0,"y":0,"w":9,"h":21},"sourceSize":{"w":9,"h":21}},"Hurt0000":{"frame":{"x":247,"y":108,"w":14,"h":19},"rotated":false,"trimmed":false,"spriteSourceSize":{"x":0,"y":0,"w":14,"h":19},"sourceSize":{"w":14,"h":19}},"Hurt0001":{"frame":{"x":281,"y":108,"w":14,"h":19},"rotated":false,"trimmed":false,"spriteSourceSize":{"x":0,"y":0,"w":14,"h":19},"sourceSize":{"w":14,"h":19}},"Hurt0002":{"frame":{"x":315,"y":108,"w":16,"h":20},"rotated":false,"trimmed":false,"spriteSourceSize":{"x":0,"y":0,"w":16,"h":20},"sourceSize":{"w":16,"h":20}},"Down0002":{"frame":{"x":44,"y":109,"w":11,"h":20},"rotated":false,"trimmed":false,"spriteSourceSize":{"x":0,"y":0,"w":11,"h":20},"sourceSize":{"w":11,"h":20}},"Down0006":{"frame":{"x":182,"y":109,"w":10,"h":20},"rotated":false,"trimmed":false,"spriteSourceSize":{"x":0,"y":0,"w":10,"h":20},"sourceSize":{"w":10,"h":20}},"Hurt0003":{"frame":{"x":7,"y":141,"w":19,"h":21},"rotated":false,"trimmed":false,"spriteSourceSize":{"x":0,"y":0,"w":19,"h":21},"sourceSize":{"w":19,"h":21}},"Disappear0001":{"frame":{"x":309,"y":141,"w":21,"h":22},"rotated":false,"trimmed":false,"spriteSourceSize":{"x":0,"y":0,"w":21,"h":22},"sourceSize":{"w":21,"h":22}},"Death0000":{"frame":{"x":44,"y":142,"w":13,"h":19},"rotated":false,"trimmed":false,"spriteSourceSize":{"x":0,"y":0,"w":13,"h":19},"sourceSize":{"w":13,"h":19}},"sprite44":{"frame":{"x":177,"y":142,"w":3,"h":3},"rotated":false,"trimmed":false,"spriteSourceSize":{"x":0,"y":0,"w":3,"h":3},"sourceSize":{"w":3,"h":3}},"sprite45":{"frame":{"x":194,"y":142,"w":3,"h":3},"rotated":false,"trimmed":false,"spriteSourceSize":{"x":0,"y":0,"w":3,"h":3},"sourceSize":{"w":3,"h":3}},"Death0004":{"frame":{"x":177,"y":143,"w":20,"h":21},"rotated":false,"trimmed":false,"spriteSourceSize":{"x":0,"y":0,"w":20,"h":21},"sourceSize":{"w":20,"h":21}},"Disappear0000":{"frame":{"x":278,"y":143,"w":16,"h":17},"rotated":false,"trimmed":false,"spriteSourceSize":{"x":0,"y":0,"w":16,"h":17},"sourceSize":{"w":16,"h":17}},"Death0001":{"frame":{"x":80,"y":144,"w":11,"h":17},"rotated":false,"trimmed":false,"spriteSourceSize":{"x":0,"y":0,"w":11,"h":17},"sourceSize":{"w":11,"h":17}},"Death0003":{"frame":{"x":147,"y":144,"w":14,"h":19},"rotated":false,"trimmed":false,"spriteSourceSize":{"x":0,"y":0,"w":14,"h":19},"sourceSize":{"w":14,"h":19}},"Death0002":{"frame":{"x":114,"y":145,"w":11,"h":16},"rotated":false,"trimmed":false,"spriteSourceSize":{"x":0,"y":0,"w":11,"h":16},"sourceSize":{"w":11,"h":16}},"sprite51":{"frame":{"x":196,"y":146,"w":1,"h":1},"rotated":false,"trimmed":false,"spriteSourceSize":{"x":0,"y":0,"w":1,"h":1},"sourceSize":{"w":1,"h":1}},"sprite52":{"frame":{"x":225,"y":148,"w":1,"h":1},"rotated":false,"trimmed":false,"spriteSourceSize":{"x":0,"y":0,"w":1,"h":1},"sourceSize":{"w":1,"h":1}},"sprite53":{"frame":{"x":215,"y":149,"w":1,"h":1},"rotated":false,"trimmed":false,"spriteSourceSize":{"x":0,"y":0,"w":1,"h":1},"sourceSize":{"w":1,"h":1}},"Death0005":{"frame":{"x":217,"y":149,"w":8,"h":7},"rotated":false,"trimmed":false,"spriteSourceSize":{"x":0,"y":0,"w":8,"h":7},"sourceSize":{"w":8,"h":7}},"sprite55":{"frame":{"x":257,"y":150,"w":1,"h":1},"rotated":false,"trimmed":false,"spriteSourceSize":{"x":0,"y":0,"w":1,"h":1},"sourceSize":{"w":1,"h":1}},"sprite56":{"frame":{"x":226,"y":151,"w":1,"h":1},"rotated":false,"trimmed":false,"spriteSourceSize":{"x":0,"y":0,"w":1,"h":1},"sourceSize":{"w":1,"h":1}},"sprite57":{"frame":{"x":252,"y":152,"w":1,"h":1},"rotated":false,"trimmed":false,"spriteSourceSize":{"x":0,"y":0,"w":1,"h":1},"sourceSize":{"w":1,"h":1}},"Death0006":{"frame":{"x":254,"y":152,"w":2,"h":2},"rotated":false,"trimmed":false,"spriteSourceSize":{"x":0,"y":0,"w":2,"h":2},"sourceSize":{"w":2,"h":2}},"sprite59":{"frame":{"x":258,"y":153,"w":1,"h":1},"rotated":false,"trimmed":false,"spriteSourceSize":{"x":0,"y":0,"w":1,"h":1},"sourceSize":{"w":1,"h":1}},"sprite60":{"frame":{"x":256,"y":155,"w":1,"h":1},"rotated":false,"trimmed":false,"spriteSourceSize":{"x":0,"y":0,"w":1,"h":1},"sourceSize":{"w":1,"h":1}},"sprite61":{"frame":{"x":216,"y":156,"w":1,"h":1},"rotated":false,"trimmed":false,"spriteSourceSize":{"x":0,"y":0,"w":1,"h":1},"sourceSize":{"w":1,"h":1}},"sprite62":{"frame":{"x":252,"y":156,"w":1,"h":1},"rotated":false,"trimmed":false,"spriteSourceSize":{"x":0,"y":0,"w":1,"h":1},"sourceSize":{"w":1,"h":1}},"sprite63":{"frame":{"x":221,"y":157,"w":1,"h":1},"rotated":false,"trimmed":false,"spriteSourceSize":{"x":0,"y":0,"w":1,"h":1},"sourceSize":{"w":1,"h":1}},"sprite64":{"frame":{"x":197,"y":159,"w":1,"h":1},"rotated":false,"trimmed":false,"spriteSourceSize":{"x":0,"y":0,"w":1,"h":1},"sourceSize":{"w":1,"h":1}},"sprite65":{"frame":{"x":191,"y":163,"w":2,"h":1},"rotated":false,"trimmed":false,"spriteSourceSize":{"x":0,"y":0,"w":2,"h":1},"sourceSize":{"w":2,"h":1}},"sprite66":{"frame":{"x":187,"y":164,"w":1,"h":1},"rotated":false,"trimmed":false,"spriteSourceSize":{"x":0,"y":0,"w":1,"h":1},"sourceSize":{"w":1,"h":1}},"Disappear0004":{"frame":{"x":73,"y":170,"w":27,"h":32},"rotated":false,"trimmed":false,"spriteSourceSize":{"x":0,"y":0,"w":27,"h":32},"sourceSize":{"w":27,"h":32}},"Disappear0003":{"frame":{"x":40,"y":172,"w":25,"h":29},"rotated":false,"trimmed":false,"spriteSourceSize":{"x":0,"y":0,"w":25,"h":29},"sourceSize":{"w":25,"h":29}},"Appear0003":{"frame":{"x":214,"y":176,"w":13,"h":19},"rotated":false,"trimmed":false,"spriteSourceSize":{"x":0,"y":0,"w":13,"h":19},"sourceSize":{"w":13,"h":19}},"Appear0002":{"frame":{"x":177,"y":177,"w":16,"h":18},"rotated":false,"trimmed":false,"spriteSourceSize":{"x":0,"y":0,"w":16,"h":18},"sourceSize":{"w":16,"h":18}},"Appear0000":{"frame":{"x":107,"y":178,"w":19,"h":17},"rotated":false,"trimmed":false,"spriteSourceSize":{"x":0,"y":0,"w":19,"h":17},"sourceSize":{"w":19,"h":17}},"Appear0001":{"frame":{"x":143,"y":178,"w":17,"h":17},"rotated":false,"trimmed":false,"spriteSourceSize":{"x":0,"y":0,"w":17,"h":17},"sourceSize":{"w":17,"h":17}},"Disappear0002":{"frame":{"x":8,"y":179,"w":17,"h":19},"rotated":false,"trimmed":false,"spriteSourceSize":{"x":0,"y":0,"w":17,"h":19},"sourceSize":{"w":17,"h":19}}},"meta":{"app":"https://www.leshylabs.com/apps/sstool/","version":"Leshy SpriteSheet Tool v0.8.4","image":"Main_Spritesheet.png","size":{"w":340,"h":204},"scale":1}}